{
  "country_name": "Italy",
  "tree": {
    "label": "country",
    "children": [
      {
        "label": "anthem",
        "children": [
          {
            "label": "Il",
            "children": []
          },
          {
            "label": "Canto",
            "children": []
          },
          {
            "label": "degli",
            "children": []
          },
          {
            "label": "Italiani",
            "children": []
          },
          {
            "label": "The",
            "children": []
          },
          {
            "label": "Song",
            "children": []
          },
          {
            "label": "of",
            "children": []
          },
          {
            "label": "the",
            "children": []
          },
          {
            "label": "Italians",
            "children": []
          }
        ],
        "raw_values": [
          "Il Canto degli Italiani \" \"The Song of the Italians"
        ]
      },
      {
        "label": "capital_and_largest_city",
        "children": [
          {
            "label": "Rome",
            "children": []
          },
          {
            "label": "41",
            "children": []
          },
          {
            "label": "54",
            "children": []
          },
          {
            "label": "N",
            "children": []
          },
          {
            "label": "12",
            "children": []
          },
          {
            "label": "29",
            "children": []
          },
          {
            "label": "E",
            "children": []
          },
          {
            "label": "41",
            "children": []
          },
          {
            "label": "900",
            "children": []
          },
          {
            "label": "N",
            "children": []
          },
          {
            "label": "12",
            "children": []
          },
          {
            "label": "483",
            "children": []
          },
          {
            "label": "E",
            "children": []
          },
          {
            "label": "41",
            "children": []
          },
          {
            "label": "900",
            "children": []
          },
          {
            "label": "12",
            "children": []
          },
          {
            "label": "483",
            "children": []
          }
        ],
        "raw_values": [
          "Rome 41°54′N 12°29′E / 41.900°N 12.483°E / 41.900; 12.483"
        ]
      },
      {
        "label": "official_languages",
        "children": [
          {
            "label": "Italian",
            "children": []
          },
          {
            "label": "a",
            "children": []
          }
        ],
        "raw_values": [
          "Italian a"
        ]
      },
      {
        "label": "nationality",
        "children": [
          {
            "label": "91",
            "children": []
          },
          {
            "label": "Italian",
            "children": []
          },
          {
            "label": "9",
            "children": []
          },
          {
            "label": "other",
            "children": []
          }
        ],
        "raw_values": [
          "91% Italian 9% other"
        ]
      },
      {
        "label": "native_languages",
        "children": [
          {
            "label": "See",
            "children": []
          },
          {
            "label": "main",
            "children": []
          },
          {
            "label": "article",
            "children": []
          }
        ],
        "raw_values": [
          "See main article"
        ]
      },
      {
        "label": "religion",
        "children": [
          {
            "label": "84",
            "children": []
          },
          {
            "label": "Christianity",
            "children": []
          },
          {
            "label": "12",
            "children": []
          },
          {
            "label": "irreligion",
            "children": []
          },
          {
            "label": "4",
            "children": []
          },
          {
            "label": "other",
            "children": []
          }
        ],
        "raw_values": [
          "84% Christianity 12% irreligion 4% other"
        ]
      },
      {
        "label": "demonyms",
        "children": [
          {
            "label": "Italian",
            "children": []
          }
        ],
        "raw_values": [
          "Italian"
        ]
      },
      {
        "label": "government",
        "children": [
          {
            "label": "Unitary",
            "children": []
          },
          {
            "label": "parliamentary",
            "children": []
          },
          {
            "label": "republic",
            "children": []
          }
        ],
        "raw_values": [
          "Unitary parliamentary republic"
        ]
      },
      {
        "label": "president",
        "children": [
          {
            "label": "Sergio",
            "children": []
          },
          {
            "label": "Mattarella",
            "children": []
          }
        ],
        "raw_values": [
          "Sergio Mattarella"
        ]
      },
      {
        "label": "prime_minister",
        "children": [
          {
            "label": "Giorgia",
            "children": []
          },
          {
            "label": "Meloni",
            "children": []
          }
        ],
        "raw_values": [
          "Giorgia Meloni"
        ]
      },
      {
        "label": "president_of_the_senate",
        "children": [
          {
            "label": "Ignazio",
            "children": []
          },
          {
            "label": "La",
            "children": []
          },
          {
            "label": "Russa",
            "children": []
          }
        ],
        "raw_values": [
          "Ignazio La Russa"
        ]
      },
      {
        "label": "president_of_the_chamber_of_deputies",
        "children": [
          {
            "label": "Lorenzo",
            "children": []
          },
          {
            "label": "Fontana",
            "children": []
          }
        ],
        "raw_values": [
          "Lorenzo Fontana"
        ]
      },
      {
        "label": "legislature",
        "children": [
          {
            "label": "Parliament",
            "children": []
          }
        ],
        "raw_values": [
          "Parliament"
        ]
      },
      {
        "label": "upper_house",
        "children": [
          {
            "label": "Senate",
            "children": []
          },
          {
            "label": "of",
            "children": []
          },
          {
            "label": "the",
            "children": []
          },
          {
            "label": "Republic",
            "children": []
          }
        ],
        "raw_values": [
          "Senate of the Republic"
        ]
      },
      {
        "label": "lower_house",
        "children": [
          {
            "label": "Chamber",
            "children": []
          },
          {
            "label": "of",
            "children": []
          },
          {
            "label": "Deputies",
            "children": []
          }
        ],
        "raw_values": [
          "Chamber of Deputies"
        ]
      },
      {
        "label": "italic_peoples",
        "children": [
          {
            "label": "Antiquity",
            "children": []
          }
        ],
        "raw_values": [
          "Antiquity"
        ]
      },
      {
        "label": "ancient_rome_roman_italy",
        "children": [
          {
            "label": "753",
            "children": []
          },
          {
            "label": "BC",
            "children": []
          },
          {
            "label": "476",
            "children": []
          },
          {
            "label": "AD",
            "children": []
          }
        ],
        "raw_values": [
          "753 BC–476 AD"
        ]
      },
      {
        "label": "romanbarbarian_kingdoms_byzantine_italy",
        "children": [
          {
            "label": "Early",
            "children": []
          },
          {
            "label": "Middle",
            "children": []
          },
          {
            "label": "Ages",
            "children": []
          }
        ],
        "raw_values": [
          "Early Middle Ages"
        ]
      },
      {
        "label": "italian_citystates_and_regional_polities",
        "children": [
          {
            "label": "Middle",
            "children": []
          },
          {
            "label": "Ages",
            "children": []
          },
          {
            "label": "and",
            "children": []
          },
          {
            "label": "Modern",
            "children": []
          },
          {
            "label": "period",
            "children": []
          }
        ],
        "raw_values": [
          "Middle Ages and Modern period"
        ]
      },
      {
        "label": "kingdom_of_italy",
        "children": [
          {
            "label": "1861",
            "children": []
          },
          {
            "label": "1946",
            "children": []
          },
          {
            "label": "17",
            "children": []
          },
          {
            "label": "March",
            "children": []
          },
          {
            "label": "1861",
            "children": []
          },
          {
            "label": "164",
            "children": []
          },
          {
            "label": "years",
            "children": []
          },
          {
            "label": "ago",
            "children": []
          },
          {
            "label": "1861",
            "children": []
          },
          {
            "label": "03",
            "children": []
          },
          {
            "label": "17",
            "children": []
          }
        ],
        "raw_values": [
          "1861–1946 17 March 1861 ; 164 years ago ( 1861-03-17 )"
        ]
      },
      {
        "label": "italian_empire",
        "children": [
          {
            "label": "1882",
            "children": []
          },
          {
            "label": "1960",
            "children": []
          }
        ],
        "raw_values": [
          "1882–1960"
        ]
      },
      {
        "label": "italian_republic",
        "children": [
          {
            "label": "2",
            "children": []
          },
          {
            "label": "June",
            "children": []
          },
          {
            "label": "1946",
            "children": []
          },
          {
            "label": "79",
            "children": []
          },
          {
            "label": "years",
            "children": []
          },
          {
            "label": "ago",
            "children": []
          },
          {
            "label": "1946",
            "children": []
          },
          {
            "label": "06",
            "children": []
          },
          {
            "label": "02",
            "children": []
          }
        ],
        "raw_values": [
          "2 June 1946 ; 79 years ago ( 1946-06-02 )"
        ]
      },
      {
        "label": "total",
        "children": [
          {
            "label": "301",
            "children": []
          },
          {
            "label": "340",
            "children": []
          },
          {
            "label": "km",
            "children": []
          },
          {
            "label": "2",
            "children": []
          },
          {
            "label": "116",
            "children": []
          },
          {
            "label": "350",
            "children": []
          },
          {
            "label": "sq",
            "children": []
          },
          {
            "label": "mi",
            "children": []
          },
          {
            "label": "71st",
            "children": []
          },
          {
            "label": "3",
            "children": []
          },
          {
            "label": "719",
            "children": []
          },
          {
            "label": "trillion",
            "children": []
          },
          {
            "label": "11th",
            "children": []
          },
          {
            "label": "2",
            "children": []
          },
          {
            "label": "423",
            "children": []
          },
          {
            "label": "trillion",
            "children": []
          },
          {
            "label": "8th",
            "children": []
          }
        ],
        "raw_values": [
          "301,340 km 2 (116,350 sq mi) ( 71st )",
          "$3.719 trillion ( 11th )",
          "$2.423 trillion ( 8th )"
        ]
      },
      {
        "label": "water",
        "children": [
          {
            "label": "1",
            "children": []
          },
          {
            "label": "24",
            "children": []
          },
          {
            "label": "2015",
            "children": []
          }
        ],
        "raw_values": [
          "1.24 (2015)"
        ]
      },
      {
        "label": "estimate",
        "children": [
          {
            "label": "58",
            "children": []
          },
          {
            "label": "915",
            "children": []
          },
          {
            "label": "561",
            "children": []
          },
          {
            "label": "25th",
            "children": []
          }
        ],
        "raw_values": [
          "58,915,561 ( 25th )"
        ]
      },
      {
        "label": "density",
        "children": [
          {
            "label": "195",
            "children": []
          },
          {
            "label": "5",
            "children": []
          },
          {
            "label": "km",
            "children": []
          },
          {
            "label": "2",
            "children": []
          },
          {
            "label": "506",
            "children": []
          },
          {
            "label": "3",
            "children": []
          },
          {
            "label": "sq",
            "children": []
          },
          {
            "label": "mi",
            "children": []
          },
          {
            "label": "72nd",
            "children": []
          }
        ],
        "raw_values": [
          "195.5/km 2 (506.3/sq mi) ( 72nd )"
        ]
      },
      {
        "label": "gdp_ppp",
        "children": [
          {
            "label": "2025",
            "children": []
          },
          {
            "label": "estimate",
            "children": []
          }
        ],
        "raw_values": [
          "2025 estimate"
        ]
      },
      {
        "label": "per_capita",
        "children": [
          {
            "label": "63",
            "children": []
          },
          {
            "label": "076",
            "children": []
          },
          {
            "label": "29th",
            "children": []
          },
          {
            "label": "41",
            "children": []
          },
          {
            "label": "091",
            "children": []
          },
          {
            "label": "27th",
            "children": []
          }
        ],
        "raw_values": [
          "$63,076 ( 29th )",
          "$41,091 ( 27th )"
        ]
      },
      {
        "label": "gdp_nominal",
        "children": [
          {
            "label": "2025",
            "children": []
          },
          {
            "label": "estimate",
            "children": []
          }
        ],
        "raw_values": [
          "2025 estimate"
        ]
      },
      {
        "label": "gini",
        "children": [
          {
            "label": "32",
            "children": []
          },
          {
            "label": "5",
            "children": []
          },
          {
            "label": "medium",
            "children": []
          },
          {
            "label": "inequality",
            "children": []
          }
        ],
        "raw_values": [
          "32.5 medium inequality"
        ]
      },
      {
        "label": "hdi",
        "children": [
          {
            "label": "0",
            "children": []
          },
          {
            "label": "915",
            "children": []
          },
          {
            "label": "very",
            "children": []
          },
          {
            "label": "high",
            "children": []
          },
          {
            "label": "29th",
            "children": []
          }
        ],
        "raw_values": [
          "0.915 very high ( 29th )"
        ]
      },
      {
        "label": "currency",
        "children": [
          {
            "label": "Euro",
            "children": []
          },
          {
            "label": "b",
            "children": []
          },
          {
            "label": "EUR",
            "children": []
          }
        ],
        "raw_values": [
          "Euro (€) b ( EUR )"
        ]
      },
      {
        "label": "time_zone",
        "children": [
          {
            "label": "UTC",
            "children": []
          },
          {
            "label": "1",
            "children": []
          },
          {
            "label": "CET",
            "children": []
          }
        ],
        "raw_values": [
          "UTC +1 ( CET )"
        ]
      },
      {
        "label": "summer_dst",
        "children": [
          {
            "label": "UTC",
            "children": []
          },
          {
            "label": "2",
            "children": []
          },
          {
            "label": "CEST",
            "children": []
          }
        ],
        "raw_values": [
          "UTC +2 ( CEST )"
        ]
      },
      {
        "label": "calling_code",
        "children": [
          {
            "label": "39",
            "children": []
          },
          {
            "label": "c",
            "children": []
          }
        ],
        "raw_values": [
          "+39 c"
        ]
      },
      {
        "label": "iso_3166_code",
        "children": [
          {
            "label": "IT",
            "children": []
          }
        ],
        "raw_values": [
          "IT"
        ]
      },
      {
        "label": "internet_tld",
        "children": [
          {
            "label": "it",
            "children": []
          }
        ],
        "raw_values": [
          ".it"
        ]
      }
    ]
  }
}