{
  "country_name": "China",
  "tree": {
    "label": "country",
    "children": [
      {
        "label": "calling_code",
        "children": [
          {
            "label": "+86 (Mainland) +852 (Hong Kong) +853 (Macau)",
            "children": []
          }
        ]
      },
      {
        "label": "capital",
        "children": [
          {
            "label": "Beijing 39°55′N 116°23′E ﻿ / ﻿ 39.917°N 116.383°E ﻿ / 39.917; 116.383",
            "children": []
          }
        ]
      },
      {
        "label": "currency",
        "children": [
          {
            "label": "Renminbi (元/¥) [ g ] ( CNY )",
            "children": []
          }
        ]
      },
      {
        "label": "demonyms",
        "children": [
          {
            "label": "Chinese",
            "children": []
          }
        ]
      },
      {
        "label": "ethnic_groups",
        "children": [
          {
            "label": "91.11% Han Chinese 1.39% Zhuang 0.84% Uyghur 0.81% Hui 0.79% Miao 0.74% Manchu 0.70% Yi 0.68% Tujia 0.50% Tibetan 2.44% others",
            "children": []
          }
        ]
      },
      {
        "label": "gdp_ppp",
        "children": [
          {
            "label": "2025 estimate",
            "children": []
          }
        ]
      },
      {
        "label": "gdp_nominal",
        "children": [
          {
            "label": "2025 estimate",
            "children": []
          }
        ]
      },
      {
        "label": "gini",
        "children": [
          {
            "label": "36.0 [ 10 ] medium inequality",
            "children": []
          }
        ]
      },
      {
        "label": "government",
        "children": [
          {
            "label": "Unitary communist state",
            "children": []
          }
        ]
      },
      {
        "label": "hdi",
        "children": [
          {
            "label": "0.797 [ 11 ] high ( 78th )",
            "children": []
          }
        ]
      },
      {
        "label": "info",
        "children": [
          {
            "label": "Flag Emblem",
            "children": []
          },
          {
            "label": "Anthem: 义勇军进行曲 Yìyǒngjūn jìnxíngqǔ \" March of the Volunteers \"",
            "children": []
          },
          {
            "label": "People's Republic of China Territory claimed but not controlled",
            "children": []
          }
        ]
      },
      {
        "label": "internet_tld",
        "children": [
          {
            "label": ".cn .中国 .中國 (Mainland) .hk .香港 (Hong Kong) .mo .澳门 .澳門 (Macau)",
            "children": []
          }
        ]
      },
      {
        "label": "iso_3166_code",
        "children": [
          {
            "label": "CN",
            "children": []
          }
        ]
      },
      {
        "label": "largest_city_by_municipal_population",
        "children": [
          {
            "label": "Chongqing [ 1 ]",
            "children": []
          }
        ]
      },
      {
        "label": "largest_city_by_urban_population",
        "children": [
          {
            "label": "Shanghai",
            "children": []
          }
        ]
      },
      {
        "label": "legislature",
        "children": [
          {
            "label": "National People's Congress [ c ]",
            "children": []
          }
        ]
      },
      {
        "label": "official_languages",
        "children": [
          {
            "label": "Standard Chinese (de facto) [ 2 ]",
            "children": []
          }
        ]
      },
      {
        "label": "official_script",
        "children": [
          {
            "label": "Simplified Chinese ( Mainland ), Traditional Chinese ( Hong Kong , Macau )",
            "children": []
          }
        ]
      },
      {
        "label": "time_zone",
        "children": [
          {
            "label": "UTC +8 ( CST )",
            "children": []
          }
        ]
      },
      {
        "label": "estimate",
        "children": [
          {
            "label": "1,404,890,000 [ e ] [ 8 ] ( 2nd )",
            "children": []
          }
        ]
      },
      {
        "label": "ccp_general_secretary_and_president",
        "children": [
          {
            "label": "Xi Jinping",
            "children": []
          }
        ]
      },
      {
        "label": "congress_chairman",
        "children": [
          {
            "label": "Zhao Leji",
            "children": []
          }
        ]
      },
      {
        "label": "cppcc_chairman",
        "children": [
          {
            "label": "Wang Huning",
            "children": []
          }
        ]
      },
      {
        "label": "current_constitution",
        "children": [
          {
            "label": "4 December 1982",
            "children": []
          }
        ]
      },
      {
        "label": "density",
        "children": [
          {
            "label": "146/km 2 (378.1/sq mi) ( 83rd )",
            "children": []
          }
        ]
      },
      {
        "label": "establishment_of_the_republic_of_china",
        "children": [
          {
            "label": "1 January 1912",
            "children": []
          }
        ]
      },
      {
        "label": "first_imperial_dynasty",
        "children": [
          {
            "label": "221 BCE",
            "children": []
          }
        ]
      },
      {
        "label": "first_preimperial_dynasty",
        "children": [
          {
            "label": "c. 2070 BCE",
            "children": []
          }
        ]
      },
      {
        "label": "per_capita",
        "children": [
          {
            "label": "$29,191 [ 9 ] ( 74th )",
            "children": []
          },
          {
            "label": "$13,806 [ 9 ] ( 75th )",
            "children": []
          }
        ]
      },
      {
        "label": "premier",
        "children": [
          {
            "label": "Li Qiang",
            "children": []
          }
        ]
      },
      {
        "label": "proclamation_of_the_peoples_republic",
        "children": [
          {
            "label": "1 October 1949",
            "children": []
          }
        ]
      },
      {
        "label": "total",
        "children": [
          {
            "label": "9,596,961 km 2 (3,705,407 sq mi) [ d ] [ 7 ] ( 3rd/4th )",
            "children": []
          },
          {
            "label": "$41.016 trillion [ f ] [ 9 ] ( 1st )",
            "children": []
          },
          {
            "label": "$19.399 trillion [ 9 ] ( 2nd )",
            "children": []
          }
        ]
      },
      {
        "label": "vice_president",
        "children": [
          {
            "label": "Han Zheng",
            "children": []
          }
        ]
      },
      {
        "label": "water",
        "children": [
          {
            "label": "2.8 [ 4 ]",
            "children": []
          }
        ]
      }
    ]
  }
}