{
  "country_name": "Namibia",
  "tree": {
    "label": "country",
    "children": [
      {
        "label": "afrikaans",
        "children": [
          {
            "label": "Republiek van Namibië [ 1 ]",
            "children": []
          }
        ]
      },
      {
        "label": "calling_code",
        "children": [
          {
            "label": "+264",
            "children": []
          }
        ]
      },
      {
        "label": "capital_and_largest_city",
        "children": [
          {
            "label": "Windhoek 22°34′S 17°5′E ﻿ / ﻿ 22.567°S 17.083°E ﻿ / -22.567; 17.083",
            "children": []
          }
        ]
      },
      {
        "label": "currency",
        "children": [
          {
            "label": "Namibian dollar (NAD) South African rand (ZAR)",
            "children": []
          }
        ]
      },
      {
        "label": "date_format",
        "children": [
          {
            "label": "dd/mm/yyyy",
            "children": []
          }
        ]
      },
      {
        "label": "demonyms",
        "children": [
          {
            "label": "Namibian",
            "children": []
          }
        ]
      },
      {
        "label": "ethnic_groups",
        "children": [
          {
            "label": "93.2% Indigenous African [ A ] 3.6% Coloured and Basters 1.8% White 1.4% Asian / other",
            "children": []
          }
        ]
      },
      {
        "label": "gdp_ppp",
        "children": [
          {
            "label": "2025 estimate",
            "children": []
          }
        ]
      },
      {
        "label": "gdp_nominal",
        "children": [
          {
            "label": "2025 estimate",
            "children": []
          }
        ]
      },
      {
        "label": "german",
        "children": [
          {
            "label": "Republik Namibia [ 2 ]",
            "children": []
          }
        ]
      },
      {
        "label": "gini",
        "children": [
          {
            "label": "59.1 [ 15 ] high inequality",
            "children": []
          }
        ]
      },
      {
        "label": "government",
        "children": [
          {
            "label": "Unitary semi-presidential republic [ 12 ] [ needs update ]",
            "children": []
          }
        ]
      },
      {
        "label": "hdi",
        "children": [
          {
            "label": "0.665 [ 16 ] medium ( 136th )",
            "children": []
          }
        ]
      },
      {
        "label": "info",
        "children": [
          {
            "label": "Flag Coat of arms",
            "children": []
          },
          {
            "label": "Motto: \"Unity, Liberty, Justice\"",
            "children": []
          },
          {
            "label": "Anthem: \" Namibia, Land of the Brave \"",
            "children": []
          },
          {
            "label": "Show globe Show map of Africa",
            "children": []
          }
        ]
      },
      {
        "label": "internet_tld",
        "children": [
          {
            "label": ".na",
            "children": []
          }
        ]
      },
      {
        "label": "iso_3166_code",
        "children": [
          {
            "label": "NA",
            "children": []
          }
        ]
      },
      {
        "label": "khoekhoegowab",
        "children": [
          {
            "label": "Republiki Namibiab dib [ 3 ]",
            "children": []
          }
        ]
      },
      {
        "label": "legislature",
        "children": [
          {
            "label": "Parliament",
            "children": []
          }
        ]
      },
      {
        "label": "official_languages",
        "children": [
          {
            "label": "English [ 9 ]",
            "children": []
          }
        ]
      },
      {
        "label": "oshiwambo",
        "children": [
          {
            "label": "Orepublika yaNamibia [ 4 ]",
            "children": []
          }
        ]
      },
      {
        "label": "otjiherero",
        "children": [
          {
            "label": "Orepublika yaNamibia [ 5 ]",
            "children": []
          }
        ]
      },
      {
        "label": "recognised_national_languages",
        "children": [
          {
            "label": "Afrikaans German Khoekhoegowab Oshiwambo Otjiherero RuKwangali Setswana siLozi",
            "children": []
          }
        ]
      },
      {
        "label": "recognised_regional_languages",
        "children": [
          {
            "label": "ǃKung Gciriku Thimbukushu",
            "children": []
          }
        ]
      },
      {
        "label": "religion",
        "children": [
          {
            "label": "87.9% Christianity 43.7% Lutheranism 22.8% Catholicism 17.0% Anglicanism 4.4% other Christian 10.5% other 1.6% no religion",
            "children": []
          }
        ]
      },
      {
        "label": "rukwangali",
        "children": [
          {
            "label": "Republika zaNamibia [ 6 ]",
            "children": []
          }
        ]
      },
      {
        "label": "setswana",
        "children": [
          {
            "label": "Rephaboliki ya Namibia [ 7 ]",
            "children": []
          }
        ]
      },
      {
        "label": "silozi",
        "children": [
          {
            "label": "Namibia ye Lukuluhile [ 8 ]",
            "children": []
          }
        ]
      },
      {
        "label": "time_zone",
        "children": [
          {
            "label": "UTC +2 ( CAT )",
            "children": []
          }
        ]
      },
      {
        "label": "census",
        "children": [
          {
            "label": "3,022,401 [ 13 ] [ 10 ] ( 136th )",
            "children": []
          }
        ]
      },
      {
        "label": "chief_justice",
        "children": [
          {
            "label": "Peter Shivute",
            "children": []
          }
        ]
      },
      {
        "label": "constitution",
        "children": [
          {
            "label": "9 February 1990",
            "children": []
          }
        ]
      },
      {
        "label": "density",
        "children": [
          {
            "label": "3.7/km 2 (9.6/sq mi)",
            "children": []
          }
        ]
      },
      {
        "label": "deputy_prime_minister",
        "children": [
          {
            "label": "Vacant",
            "children": []
          }
        ]
      },
      {
        "label": "independence",
        "children": [
          {
            "label": "21 March 1990",
            "children": []
          }
        ]
      },
      {
        "label": "lower_house",
        "children": [
          {
            "label": "National Assembly",
            "children": []
          }
        ]
      },
      {
        "label": "per_capita",
        "children": [
          {
            "label": "$12,370 [ 14 ] ( 117th )",
            "children": []
          },
          {
            "label": "$4,660 [ 14 ] ( 120th )",
            "children": []
          }
        ]
      },
      {
        "label": "president",
        "children": [
          {
            "label": "Netumbo Nandi-Ndaitwah",
            "children": []
          }
        ]
      },
      {
        "label": "prime_minister",
        "children": [
          {
            "label": "Elijah Ngurare",
            "children": []
          }
        ]
      },
      {
        "label": "total",
        "children": [
          {
            "label": "825,615 km 2 (318,772 sq mi) ( 34th )",
            "children": []
          },
          {
            "label": "$37.73 billion [ 14 ] ( 145th )",
            "children": []
          },
          {
            "label": "$14.21 billion [ 14 ] ( 145th )",
            "children": []
          }
        ]
      },
      {
        "label": "upper_house",
        "children": [
          {
            "label": "National Council",
            "children": []
          }
        ]
      },
      {
        "label": "vice_president",
        "children": [
          {
            "label": "Lucia Witbooi",
            "children": []
          }
        ]
      },
      {
        "label": "water",
        "children": [
          {
            "label": "Negligible",
            "children": []
          }
        ]
      }
    ]
  }
}