{
  "country_name": "Singapore",
  "tree": {
    "label": "country",
    "children": [
      {
        "label": "info",
        "children": [
          {
            "label": "Flag Coat of arms",
            "children": []
          },
          {
            "label": "Motto: Majulah Singapura ( Malay ) \"Onward Singapore\"",
            "children": []
          },
          {
            "label": "Anthem: Majulah Singapura ( Malay ) \"Onward Singapore\"",
            "children": []
          },
          {
            "label": "Show globe Show ASEAN Location of Singapore (green) in Southeast Asia",
            "children": []
          }
        ]
      },
      {
        "label": "capital",
        "children": [
          {
            "label": "Singapore ( city-state ) 1°17′N 103°50′E / 1.283°N 103.833°E / 1.283; 103.833",
            "children": []
          }
        ]
      },
      {
        "label": "largest_planning_area_by_population",
        "children": [
          {
            "label": "Tampines",
            "children": []
          }
        ]
      },
      {
        "label": "official_languages",
        "children": [
          {
            "label": "English Malay Mandarin Tamil",
            "children": []
          }
        ]
      },
      {
        "label": "national_language",
        "children": [
          {
            "label": "Malay",
            "children": []
          }
        ]
      },
      {
        "label": "ethnic_groups",
        "children": [
          {
            "label": "74.3% Chinese 13.5% Malay 9.0% Indian 3.2% Other",
            "children": []
          }
        ]
      },
      {
        "label": "religion",
        "children": [
          {
            "label": "31.1% Buddhism 20.0% No religion 18.9% Christianity 15.6% Islam 8.8% Taoism 5.0% Hinduism 0.3% Sikhism 0.3% Other",
            "children": []
          }
        ]
      },
      {
        "label": "demonyms",
        "children": [
          {
            "label": "Singaporean",
            "children": []
          }
        ]
      },
      {
        "label": "government",
        "children": [
          {
            "label": "Unitary parliamentary republic",
            "children": []
          }
        ]
      },
      {
        "label": "president",
        "children": [
          {
            "label": "Tharman Shanmugaratnam",
            "children": []
          }
        ]
      },
      {
        "label": "prime_minister",
        "children": [
          {
            "label": "Lawrence Wong",
            "children": []
          }
        ]
      },
      {
        "label": "legislature",
        "children": [
          {
            "label": "Parliament",
            "children": []
          }
        ]
      },
      {
        "label": "selfgovernance",
        "children": [
          {
            "label": "3 June 1959",
            "children": []
          }
        ]
      },
      {
        "label": "malaysia_agreement",
        "children": [
          {
            "label": "16 September 1963",
            "children": []
          }
        ]
      },
      {
        "label": "proclamation_of_singapore",
        "children": [
          {
            "label": "9 August 1965",
            "children": []
          }
        ]
      },
      {
        "label": "total",
        "children": [
          {
            "label": "744.3 km 2 (287.4 sq mi) ( 176th )",
            "children": []
          },
          {
            "label": "$952.600 billion ( 34th )",
            "children": []
          },
          {
            "label": "$564.700 billion ( 27th )",
            "children": []
          }
        ]
      },
      {
        "label": "water",
        "children": [
          {
            "label": "1.43%",
            "children": []
          }
        ]
      },
      {
        "label": "estimate",
        "children": [
          {
            "label": "6,110,200 ( 111th )",
            "children": []
          }
        ]
      },
      {
        "label": "density",
        "children": [
          {
            "label": "8,290/km 2 (21,471.0/sq mi) ( 3rd )",
            "children": []
          }
        ]
      },
      {
        "label": "gdp_ppp",
        "children": [
          {
            "label": "2025 estimate",
            "children": []
          }
        ]
      },
      {
        "label": "per_capita",
        "children": [
          {
            "label": "$156,755 ( 1st )",
            "children": []
          },
          {
            "label": "$93,956 ( 4th )",
            "children": []
          }
        ]
      },
      {
        "label": "gdp_nominal",
        "children": [
          {
            "label": "2025 estimate",
            "children": []
          }
        ]
      },
      {
        "label": "gini",
        "children": [
          {
            "label": "43.3 medium inequality",
            "children": []
          }
        ]
      },
      {
        "label": "hdi",
        "children": [
          {
            "label": "0.946 very high ( 13th )",
            "children": []
          }
        ]
      },
      {
        "label": "currency",
        "children": [
          {
            "label": "Singapore dollar (S$) ( SGD )",
            "children": []
          }
        ]
      },
      {
        "label": "time_zone",
        "children": [
          {
            "label": "UTC +8 ( SGT )",
            "children": []
          }
        ]
      },
      {
        "label": "date_format",
        "children": [
          {
            "label": "dd-mm-yyyy ( AD )",
            "children": []
          }
        ]
      },
      {
        "label": "calling_code",
        "children": [
          {
            "label": "+65",
            "children": []
          }
        ]
      },
      {
        "label": "iso_3166_code",
        "children": [
          {
            "label": "SG",
            "children": []
          }
        ]
      },
      {
        "label": "internet_tld",
        "children": [
          {
            "label": ".sg",
            "children": []
          }
        ]
      }
    ]
  }
}